config/__init__.py
py_app_config-1.0.0.dist-info/DESCRIPTION.rst
py_app_config-1.0.0.dist-info/METADATA
py_app_config-1.0.0.dist-info/RECORD
py_app_config-1.0.0.dist-info/WHEEL
py_app_config-1.0.0.dist-info/metadata.json
py_app_config-1.0.0.dist-info/top_level.txt
py_config/__init__.py
